tud_sumo/__init__.py
tud_sumo/controllers.py
tud_sumo/demand.py
tud_sumo/events.py
tud_sumo/plot.py
tud_sumo/simulation.py
tud_sumo/utils.py
tud_sumo/videos.py
tud_sumo-3.3.0.dist-info/METADATA
tud_sumo-3.3.0.dist-info/WHEEL
tud_sumo-3.3.0.dist-info/licenses/LICENSE
tud_sumo-3.3.0.dist-info/RECORD
