Metadata-Version: 2.4
Name: tud-sumo
Version: 3.3.0
Summary: A Research-oriented wrapper for SUMO developed at TU Delft
Project-URL: Documentation, https://tud-sumo.github.io/docs/
Project-URL: Repository, https://github.com/DAIMoNDLab/tud-sumo
Project-URL: Example Code, https://github.com/DAIMoNDLab/tud-sumo-examples
Author-email: Callum Evans <c.evans@tudelft.nl>
License:                                  Apache License
License-File: LICENSE
Keywords: SUMO,microscopic,traffic simulator
Classifier: Development Status :: 4 - Beta
Classifier: Intended Audience :: Science/Research
Classifier: License :: OSI Approved :: Apache Software License
Classifier: Programming Language :: Python :: 3
Classifier: Programming Language :: Python :: 3.10
Classifier: Programming Language :: Python :: 3.11
Classifier: Programming Language :: Python :: 3.12
Classifier: Programming Language :: Python :: 3.13
Classifier: Programming Language :: Python :: 3.14
Classifier: Topic :: Scientific/Engineering
Requires-Python: >=3.10
Requires-Dist: matplotlib
Requires-Dist: moviepy
Requires-Dist: mpl-tools
Requires-Dist: numpy
Requires-Dist: requests
Requires-Dist: shapely
Requires-Dist: tqdm
Requires-Dist: traci
Provides-Extra: test
Requires-Dist: pytest; extra == 'test'
Requires-Dist: pytest-cov; extra == 'test'
